simplenotifications/__init__.py
simplenotifications/mail.py
simplenotifications/webhook.py
simple_notifications-0.1.3.dist-info/LICENSE.txt
simple_notifications-0.1.3.dist-info/METADATA
simple_notifications-0.1.3.dist-info/WHEEL
simple_notifications-0.1.3.dist-info/top_level.txt
simple_notifications-0.1.3.dist-info/RECORD
