Metadata-Version: 2.1
Name: simple-notifications
Version: 0.1.3
Summary: Send notfications by email or webhook
Author: Christoph Stein
License: MIT
Project-URL: homepage, https://gitlab.com/s7one/simple-notifications
Project-URL: documentation, https://s7one.gitlab.io/simple-notifications
Project-URL: repository, https://gitlab.com/s7one/simple-notifications
Keywords: Email,Notifications
Classifier: Programming Language :: Python :: 3
Classifier: Development Status :: 4 - Beta
Classifier: Environment :: Console
Requires-Python: >=3.9
License-File: LICENSE.txt
